py_sv_parser-0.3.0.dist-info/METADATA
py_sv_parser-0.3.0.dist-info/WHEEL
py_sv_parser.cpython-37m-x86_64-linux-gnu.so
py_sv_parser-0.3.0.dist-info/RECORD
