Metadata-Version: 2.1
Name: py_sv_parser
Version: 0.3.0
Summary: Python bindings for SystemVerilog parsing.
Author: David Lenfesty <david.lenfesty@eideticom.com>
Author-Email: David Lenfesty <david.lenfesty@eideticom.com>
Maintainer: David Lenfesty
Maintainer-Email: david.lenfesty@eideticom.com
Project-URL: Homepage, https://github.com/Eideticom/py-sv-parser
